.hgtags
MANIFEST.in
README.txt
setup.cfg
setup.py
collective/__init__.py
collective.portlet.calendar.egg-info/PKG-INFO
collective.portlet.calendar.egg-info/SOURCES.txt
collective.portlet.calendar.egg-info/dependency_links.txt
collective.portlet.calendar.egg-info/entry_points.txt
collective.portlet.calendar.egg-info/namespace_packages.txt
collective.portlet.calendar.egg-info/not-zip-safe
collective.portlet.calendar.egg-info/requires.txt
collective.portlet.calendar.egg-info/top_level.txt
collective/portlet/__init__.py
collective/portlet/calendar/README.txt
collective/portlet/calendar/__init__.py
collective/portlet/calendar/calendar.pt
collective/portlet/calendar/calendar.py
collective/portlet/calendar/config.py
collective/portlet/calendar/configure.zcml
collective/portlet/calendar/setuphandlers.py
collective/portlet/calendar/version.txt
collective/portlet/calendar/browser/__init__.py
collective/portlet/calendar/browser/configure.zcml
collective/portlet/calendar/browser/interfaces.py
collective/portlet/calendar/browser/calendar_styles/calendar.css
collective/portlet/calendar/docs/__init__.py
collective/portlet/calendar/docs/browser.txt
collective/portlet/calendar/locales/collective.portlet.calendar.pot
collective/portlet/calendar/locales/generateMo.sh
collective/portlet/calendar/locales/manual.pot
collective/portlet/calendar/locales/rebuildAll.sh
collective/portlet/calendar/locales/it/LC_MESSAGES/collective.portlet.calendar.po
collective/portlet/calendar/locales/pt_BR/LC_MESSAGES/collective.portlet.calendar.po
collective/portlet/calendar/profiles/default/browserlayer.xml
collective/portlet/calendar/profiles/default/collective.portlet.calendar.txt
collective/portlet/calendar/profiles/default/cssregistry.xml
collective/portlet/calendar/profiles/default/import_steps.xml
collective/portlet/calendar/profiles/default/metadata.xml
collective/portlet/calendar/profiles/default/portlets.xml
collective/portlet/calendar/profiles/uninstall/browserlayer.xml
collective/portlet/calendar/profiles/uninstall/collective.portlet.calendar.txt
collective/portlet/calendar/profiles/uninstall/cssregistry.xml
collective/portlet/calendar/profiles/uninstall/portlets.xml
collective/portlet/calendar/tests/__init__.py
collective/portlet/calendar/tests/test_calendarex.py
collective/portlet/calendar/tests/test_functional.py
collective/portlet/calendar/upgrades/__init__.py
