Metadata-Version: 1.0
Name: collective.portlet.calendar
Version: 0.6
Summary: Extended Calendar Portlet: A configurable implementation of a Calendar Portlet for Plone.
Home-page: https://bitbucket.org/simplesconsultoria/collective.portlet.calendar
Author: Simples Consultoria
Author-email: products@simplesconsultoria.com.br
License: GPL
Keywords: plone plone4 portlet calendar web
Platform: UNKNOWN
Classifier: Framework :: Plone
Classifier: Framework :: Zope2
Classifier: Framework :: Zope3
Classifier: Programming Language :: Python
Classifier: Topic :: Software Development :: Libraries :: Python Modules
